[{"SEQUENCE":1,"CITY":"WASHINGTON","STATE":"DC","DATE_TIME":"DEC/22/2015 06 AM","UV_VALUE":0},{"SEQUENCE":2,"CITY":"WASHINGTON","STATE":"DC","DATE_TIME":"DEC/22/2015 07 AM","UV_VALUE":0},{"SEQUENCE":3,"CITY":"WASHINGTON","STATE":"DC","DATE_TIME":"DEC/22/2015 08 AM","UV_VALUE":0},{"SEQUENCE":4,"CITY":"WASHINGTON","STATE":"DC","DATE_TIME":"DEC/22/2015 09 AM","UV_VALUE":0},{"SEQUENCE":5,"CITY":"WASHINGTON","STATE":"DC","DATE_TIME":"DEC/22/2015 10 AM","UV_VALUE":0},{"SEQUENCE":6,"CITY":"WASHINGTON","STATE":"DC","DATE_TIME":"DEC/22/2015 11 AM","UV_VALUE":1},{"SEQUENCE":7,"CITY":"WASHINGTON","STATE":"DC","DATE_TIME":"DEC/22/2015 12 PM","UV_VALUE":1},{"SEQUENCE":8,"CITY":"WASHINGTON","STATE":"DC","DATE_TIME":"DEC/22/2015 01 PM","UV_VALUE":1},{"SEQUENCE":9,"CITY":"WASHINGTON","STATE":"DC","DATE_TIME":"DEC/22/2015 02 PM","UV_VALUE":1},{"SEQUENCE":10,"CITY":"WASHINGTON","STATE":"DC","DATE_TIME":"DEC/22/2015 03 PM","UV_VALUE":0},{"SEQUENCE":11,"CITY":"WASHINGTON","STATE":"DC","DATE_TIME":"DEC/22/2015 04 PM","UV_VALUE":0},{"SEQUENCE":12,"CITY":"WASHINGTON","STATE":"DC","DATE_TIME":"DEC/22/2015 05 PM","UV_VALUE":0},{"SEQUENCE":13,"CITY":"WASHINGTON","STATE":"DC","DATE_TIME":"DEC/22/2015 06 PM","UV_VALUE":0},{"SEQUENCE":14,"CITY":"WASHINGTON","STATE":"DC","DATE_TIME":"DEC/22/2015 07 PM","UV_VALUE":0},{"SEQUENCE":15,"CITY":"WASHINGTON","STATE":"DC","DATE_TIME":"DEC/22/2015 08 PM","UV_VALUE":0},{"SEQUENCE":16,"CITY":"WASHINGTON","STATE":"DC","DATE_TIME":"DEC/22/2015 09 PM","UV_VALUE":0},{"SEQUENCE":17,"CITY":"WASHINGTON","STATE":"DC","DATE_TIME":"DEC/22/2015 10 PM","UV_VALUE":0},{"SEQUENCE":18,"CITY":"WASHINGTON","STATE":"DC","DATE_TIME":"DEC/22/2015 11 PM","UV_VALUE":0},{"SEQUENCE":19,"CITY":"WASHINGTON","STATE":"DC","DATE_TIME":"DEC/22/2015 12 AM","UV_VALUE":0},{"SEQUENCE":20,"CITY":"WASHINGTON","STATE":"DC","DATE_TIME":"DEC/22/2015 01 AM","UV_VALUE":0},{"SEQUENCE":21,"CITY":"WASHINGTON","STATE":"DC","DATE_TIME":"DEC/22/2015 02 AM","UV_VALUE":0}]
